autodistill_sam_clip/__init__.py
autodistill_sam_clip/helpers.py
autodistill_sam_clip/sam_clip.py
autodistill_sam_clip-0.1.3.dist-info/LICENSE
autodistill_sam_clip-0.1.3.dist-info/METADATA
autodistill_sam_clip-0.1.3.dist-info/WHEEL
autodistill_sam_clip-0.1.3.dist-info/top_level.txt
autodistill_sam_clip-0.1.3.dist-info/RECORD
